notionflow/__init__.py
notionflow/client.py
notionflow/fluent.py
notionflow/models/__init__.py
notionflow/models/database_info.py
notionflow/models/page_info.py
notionflow/models/run_schema.py
notionflow/page.py
notionflow/report.py
notionflow-0.1.0.dist-info/LICENSE
notionflow-0.1.0.dist-info/METADATA
notionflow-0.1.0.dist-info/WHEEL
notionflow-0.1.0.dist-info/RECORD
