Metadata-Version: 2.1
Name: notionflow
Version: 0.1.0
Summary: 
License: MIT
Author: nekanat
Author-email: nekanat.stock@gmail.com
Requires-Python: >=3.9,<4.0
Classifier: License :: OSI Approved :: MIT License
Classifier: Programming Language :: Python :: 3
Classifier: Programming Language :: Python :: 3.9
Classifier: Programming Language :: Python :: 3.10
Classifier: Programming Language :: Python :: 3.11
Requires-Dist: notion-client (>=2.0.0,<3.0.0)
Requires-Dist: plotly (>=5.14.1,<6.0.0)
Requires-Dist: pydantic (>=1.10.7,<2.0.0)
